platform_observability/__init__.py
platform_observability/cli.py
platform_observability/client.py
platform_observability/exceptions.py
platform_observability/logger.py
platform_observability/models.py
redducklabs_platform_observability_sdk-1.0.0.dist-info/METADATA
redducklabs_platform_observability_sdk-1.0.0.dist-info/WHEEL
redducklabs_platform_observability_sdk-1.0.0.dist-info/entry_points.txt
redducklabs_platform_observability_sdk-1.0.0.dist-info/top_level.txt
redducklabs_platform_observability_sdk-1.0.0.dist-info/RECORD
